{"title":"","slug":"推荐/午后阳光","date":"2022-04-10T04:49:05.417Z","updated":"2019-11-19T06:44:25.604Z","comments":true,"path":"api/articles/推荐/午后阳光.json","excerpt":null,"covers":null,"content":"<h4 id=\"午后阳光\"><a href=\"#午后阳光\" class=\"headerlink\" title=\"午后阳光\"></a>午后阳光</h4><p>我喜欢秋日的阳光，特别喜欢。阳光打在身上，暖暖的，驱散了有点寒冷的秋意。闭上眼睛，沐浴在阳光中，似乎在一望无垠的光海中荡漾，没有远方，没有过往。忘却一切，万物皆空。</p>\n<p>梧桐叶落，一片一片。黄色的树叶在风中摇拽，沙沙的声音，是大自然在低语。生活不必太匆忙，过于焦虑。总是身处在喧杂的环境中，人容易憔悴。</p>\n<p>美好，就是午后的一缕阳光。</p>\n","more":"<h4 id=\"午后阳光\"><a href=\"#午后阳光\" class=\"headerlink\" title=\"午后阳光\"></a>午后阳光</h4><p>我喜欢秋日的阳光，特别喜欢。阳光打在身上，暖暖的，驱散了有点寒冷的秋意。闭上眼睛，沐浴在阳光中，似乎在一望无垠的光海中荡漾，没有远方，没有过往。忘却一切，万物皆空。</p>\n<p>梧桐叶落，一片一片。黄色的树叶在风中摇拽，沙沙的声音，是大自然在低语。生活不必太匆忙，过于焦虑。总是身处在喧杂的环境中，人容易憔悴。</p>\n<p>美好，就是午后的一缕阳光。</p>\n","categories":[],"tags":[]}